.gitignore
CHANGES.txt
MANIFEST.in
README.rst
bootstrap.py
buildout.cfg
setup.py
collective/__init__.py
collective.js.imagesloaded.egg-info/PKG-INFO
collective.js.imagesloaded.egg-info/SOURCES.txt
collective.js.imagesloaded.egg-info/dependency_links.txt
collective.js.imagesloaded.egg-info/entry_points.txt
collective.js.imagesloaded.egg-info/namespace_packages.txt
collective.js.imagesloaded.egg-info/not-zip-safe
collective.js.imagesloaded.egg-info/requires.txt
collective.js.imagesloaded.egg-info/top_level.txt
collective/js/__init__.py
collective/js/imagesloaded/__init__.py
collective/js/imagesloaded/configure.zcml
collective/js/imagesloaded/upgrades.py
collective/js/imagesloaded/upgrades.zcml
collective/js/imagesloaded/profiles/default/jsregistry.xml
collective/js/imagesloaded/profiles/default/metadata.xml
collective/js/imagesloaded/resources/jquery.imagesloaded.js