Metadata-Version: 1.0
Name: collective.js.imagesloaded
Version: 2.1
Summary: Register JQuery imagesloaded plugin in Plone resource registry
Home-page: https://github.com/collective/collective.js.imagesloaded
Author: JeanMichel FRANCOIS aka toutpt
Author-email: toutpt@gmail.com
License: GPL
Keywords: plone javascripts imagesloaded
Platform: UNKNOWN
Classifier: Environment :: Web Environment
Classifier: License :: OSI Approved :: GNU General Public License (GPL)
Classifier: Operating System :: OS Independent
Classifier: Framework :: Plone
Classifier: Framework :: Plone :: 4.0
Classifier: Framework :: Plone :: 4.1
Classifier: Framework :: Plone :: 4.2
Classifier: Programming Language :: Python
